{
    "projectId": "C5232",
    "client": "Sonalika",
    "planning": {
        "value": 29766,
        "budget": 20836,
        "deliveryTerms": "ToPay",
        "poConfirmed": false,
        "startDate": "2026-06-12"
    },
    "production": {
        "currentStage": "Workshop Fabrication",
        "stages": [
            {
                "name": "Engineering Design",
                "status": "Completed",
                "lead": "Devanshu"
            },
            {
                "name": "Machine Processing",
                "status": "Completed",
                "lead": "Paras"
            },
            {
                "name": "Workshop Fabrication",
                "status": "In Progress",
                "lead": "Parth"
            },
            {
                "name": "Sanding",
                "status": "Pending",
                "lead": "Parth"
            },
            {
                "name": "Painting",
                "status": "Pending",
                "lead": "Parth"
            },
            {
                "name": "Drying",
                "status": "Pending",
                "lead": "Parth"
            },
            {
                "name": "Finishing",
                "status": "Pending",
                "lead": "Parth"
            },
            {
                "name": "Final Packaging",
                "status": "Pending",
                "lead": "Devanshu"
            }
        ]
    },
    "metrics": {
        "totalComponents": 5,
        "materialConsumption": "MJF Black Paint",
        "workforce": [
            "Devanshu",
            "Anurag",
            "Devyanshu"
        ]
    },
    "financials": {
        "vendorName": "excel Rapid Tech",
        "vendorLocation": "Delhi",
        "dispatchBudget": 0,
        "totalCost": null,
        "profitLoss": null,
        "deliveryFeeMode": "To pay basis",
        "poNumber": "QT-18232"
    },
    "dailyStandup": {
        "srNo": "=1+A11",
        "discussingNotes": "5 | excel Rapid Tech | QC: Dispatched to customer; Feedback on Thursday",
        "preparingPartsDate": "2026-06-26",
        "routeFrom": "Delhi",
        "routeTo": "Englabs",
        "porterPayments": 168,
        "inputsRequired": "NO",
        "supervisor": "Devyanshu"
    },
    "poRelease": {
        "customerSalePrice": 29766,
        "vendorName": "excel Rapid Tech",
        "vendorLocation": "Delhi",
        "poVendorSent": "N/A",
        "vendorCost": 168,
        "releaseDate": "2026-06-12"
    },
    "invoiceRelease": {
        "gstRate": 18,
        "gstValue": 5358,
        "totalInvoiceAmount": 35124,
        "paymentTerms": "30 days",
        "invoiceNumber": "QT-18232",
        "paymentStatus": "Pending"
    }
}